enochecker/__init__.py
enochecker/checkerservice.py
enochecker/enochecker.py
enochecker/logging.py
enochecker/nosqldict.py
enochecker/post.html
enochecker/py.typed
enochecker/results.py
enochecker/storeddict.py
enochecker/useragents.py
enochecker/utils.py
enochecker-0.5.0.dist-info/LICENSE
enochecker-0.5.0.dist-info/METADATA
enochecker-0.5.0.dist-info/WHEEL
enochecker-0.5.0.dist-info/top_level.txt
enochecker-0.5.0.dist-info/RECORD
