Metadata-Version: 2.1
Name: enochecker
Version: 0.5.0
Summary: Library to build checker scripts for EnoEngine A/D CTF Framework in Python
Home-page: https://github.com/ENOWARS/enochecker
Author: domenukk
Author-email: dmaier@sect.tu-berlin.de
License: UNKNOWN
Platform: UNKNOWN
Classifier: Development Status :: 3 - Alpha
Classifier: License :: OSI Approved :: MIT License
Classifier: Programming Language :: Python :: 3.7
Classifier: Programming Language :: Python :: 3.8
Classifier: Programming Language :: Python :: 3.9
Requires-Python: >=3.7
License-File: LICENSE
Requires-Dist: certifi (==2020.12.5)
Requires-Dist: chardet (==4.0.0)
Requires-Dist: click (==7.1.2)
Requires-Dist: enochecker-cli (==0.7.0)
Requires-Dist: enochecker-core (==0.10.0)
Requires-Dist: Flask (==1.1.2)
Requires-Dist: idna (==2.10)
Requires-Dist: itsdangerous (==1.1.0)
Requires-Dist: Jinja2 (==2.11.3)
Requires-Dist: jsons (==1.4.2)
Requires-Dist: MarkupSafe (==1.1.1)
Requires-Dist: pymongo (==3.11.3)
Requires-Dist: requests (==2.25.1)
Requires-Dist: typish (==1.9.2)
Requires-Dist: urllib3 (==1.26.5)
Requires-Dist: Werkzeug (==1.0.1)
Requires-Dist: pwntools (==4.5.0)
